{"nodes": [{"id": "c_users_ubaiy_back_myb_project_apps_admin_src_app_features_inspections_shared_inspection_labels_ts", "label": "inspection-labels.ts", "file_type": "code", "source_file": "C:\\Users\\UBAIY\\Back\\MYB\\Project\\apps\\admin\\src\\app\\features\\inspections\\shared\\inspection-labels.ts", "source_location": "L1"}, {"id": "shared_inspection_labels_kind_labels", "label": "KIND_LABELS", "file_type": "code", "source_file": "C:\\Users\\UBAIY\\Back\\MYB\\Project\\apps\\admin\\src\\app\\features\\inspections\\shared\\inspection-labels.ts", "source_location": "L12"}, {"id": "shared_inspection_labels_kind_chip_class", "label": "KIND_CHIP_CLASS", "file_type": "code", "source_file": "C:\\Users\\UBAIY\\Back\\MYB\\Project\\apps\\admin\\src\\app\\features\\inspections\\shared\\inspection-labels.ts", "source_location": "L17"}, {"id": "shared_inspection_labels_status_labels", "label": "STATUS_LABELS", "file_type": "code", "source_file": "C:\\Users\\UBAIY\\Back\\MYB\\Project\\apps\\admin\\src\\app\\features\\inspections\\shared\\inspection-labels.ts", "source_location": "L22"}, {"id": "shared_inspection_labels_status_chip_class", "label": "STATUS_CHIP_CLASS", "file_type": "code", "source_file": "C:\\Users\\UBAIY\\Back\\MYB\\Project\\apps\\admin\\src\\app\\features\\inspections\\shared\\inspection-labels.ts", "source_location": "L30"}, {"id": "shared_inspection_labels_item_status_labels", "label": "ITEM_STATUS_LABELS", "file_type": "code", "source_file": "C:\\Users\\UBAIY\\Back\\MYB\\Project\\apps\\admin\\src\\app\\features\\inspections\\shared\\inspection-labels.ts", "source_location": "L38"}, {"id": "shared_inspection_labels_item_status_on_class", "label": "ITEM_STATUS_ON_CLASS", "file_type": "code", "source_file": "C:\\Users\\UBAIY\\Back\\MYB\\Project\\apps\\admin\\src\\app\\features\\inspections\\shared\\inspection-labels.ts", "source_location": "L45"}], "edges": [{"source": "c_users_ubaiy_back_myb_project_apps_admin_src_app_features_inspections_shared_inspection_labels_ts", "target": "c_users_ubaiy_back_myb_project_libs_shared_types_src_index_ts", "relation": "imports_from", "context": "import", "confidence": "EXTRACTED", "source_file": "C:\\Users\\UBAIY\\Back\\MYB\\Project\\apps\\admin\\src\\app\\features\\inspections\\shared\\inspection-labels.ts", "source_location": "L1", "weight": 1.0}, {"source": "c_users_ubaiy_back_myb_project_apps_admin_src_app_features_inspections_shared_inspection_labels_ts", "target": "src_index_inspectionitemstatus", "relation": "imports", "context": "import", "confidence": "EXTRACTED", "source_file": "C:\\Users\\UBAIY\\Back\\MYB\\Project\\apps\\admin\\src\\app\\features\\inspections\\shared\\inspection-labels.ts", "source_location": "L1", "weight": 1.0}, {"source": "c_users_ubaiy_back_myb_project_apps_admin_src_app_features_inspections_shared_inspection_labels_ts", "target": "src_index_inspectionkind", "relation": "imports", "context": "import", "confidence": "EXTRACTED", "source_file": "C:\\Users\\UBAIY\\Back\\MYB\\Project\\apps\\admin\\src\\app\\features\\inspections\\shared\\inspection-labels.ts", "source_location": "L1", "weight": 1.0}, {"source": "c_users_ubaiy_back_myb_project_apps_admin_src_app_features_inspections_shared_inspection_labels_ts", "target": "src_index_inspectionstatus", "relation": "imports", "context": "import", "confidence": "EXTRACTED", "source_file": "C:\\Users\\UBAIY\\Back\\MYB\\Project\\apps\\admin\\src\\app\\features\\inspections\\shared\\inspection-labels.ts", "source_location": "L1", "weight": 1.0}, {"source": "c_users_ubaiy_back_myb_project_apps_admin_src_app_features_inspections_shared_inspection_labels_ts", "target": "shared_inspection_labels_kind_labels", "relation": "contains", "confidence": "EXTRACTED", "source_file": "C:\\Users\\UBAIY\\Back\\MYB\\Project\\apps\\admin\\src\\app\\features\\inspections\\shared\\inspection-labels.ts", "source_location": "L12", "weight": 1.0}, {"source": "c_users_ubaiy_back_myb_project_apps_admin_src_app_features_inspections_shared_inspection_labels_ts", "target": "shared_inspection_labels_kind_chip_class", "relation": "contains", "confidence": "EXTRACTED", "source_file": "C:\\Users\\UBAIY\\Back\\MYB\\Project\\apps\\admin\\src\\app\\features\\inspections\\shared\\inspection-labels.ts", "source_location": "L17", "weight": 1.0}, {"source": "c_users_ubaiy_back_myb_project_apps_admin_src_app_features_inspections_shared_inspection_labels_ts", "target": "shared_inspection_labels_status_labels", "relation": "contains", "confidence": "EXTRACTED", "source_file": "C:\\Users\\UBAIY\\Back\\MYB\\Project\\apps\\admin\\src\\app\\features\\inspections\\shared\\inspection-labels.ts", "source_location": "L22", "weight": 1.0}, {"source": "c_users_ubaiy_back_myb_project_apps_admin_src_app_features_inspections_shared_inspection_labels_ts", "target": "shared_inspection_labels_status_chip_class", "relation": "contains", "confidence": "EXTRACTED", "source_file": "C:\\Users\\UBAIY\\Back\\MYB\\Project\\apps\\admin\\src\\app\\features\\inspections\\shared\\inspection-labels.ts", "source_location": "L30", "weight": 1.0}, {"source": "c_users_ubaiy_back_myb_project_apps_admin_src_app_features_inspections_shared_inspection_labels_ts", "target": "shared_inspection_labels_item_status_labels", "relation": "contains", "confidence": "EXTRACTED", "source_file": "C:\\Users\\UBAIY\\Back\\MYB\\Project\\apps\\admin\\src\\app\\features\\inspections\\shared\\inspection-labels.ts", "source_location": "L38", "weight": 1.0}, {"source": "c_users_ubaiy_back_myb_project_apps_admin_src_app_features_inspections_shared_inspection_labels_ts", "target": "shared_inspection_labels_item_status_on_class", "relation": "contains", "confidence": "EXTRACTED", "source_file": "C:\\Users\\UBAIY\\Back\\MYB\\Project\\apps\\admin\\src\\app\\features\\inspections\\shared\\inspection-labels.ts", "source_location": "L45", "weight": 1.0}], "raw_calls": []}